{"created":26,"villages":[{"id":29,"tile_id":511,"land_chunk_index":44,"name":"Village 511-44","housing_slots":[],"created_at":"2026-01-25T12:16:18.611Z","updated_at":"2026-01-25T12:16:18.611Z"},{"id":30,"tile_id":1346,"land_chunk_index":2,"name":"Village 1346-2","housing_slots":[],"created_at":"2026-01-25T12:16:18.611Z","updated_at":"2026-01-25T12:16:18.611Z"},{"id":31,"tile_id":1204,"land_chunk_index":50,"name":"Village 1204-50","housing_slots":[],"created_at":"2026-01-25T12:16:18.611Z","updated_at":"2026-01-25T12:16:18.611Z"},{"id":32,"tile_id":497,"land_chunk_index":2,"name":"Village 497-2","housing_slots":[],"created_at":"2026-01-25T12:16:18.611Z","updated_at":"2026-01-25T12:16:18.611Z"},{"id":33,"tile_id":1204,"land_chunk_index":16,"name":"Village 1204-16","housing_slots":[],"created_at":"2026-01-25T12:16:18.611Z","updated_at":"2026-01-25T12:16:18.611Z"},{"id":34,"tile_id":1198,"land_chunk_index":19,"name":"Village 1198-19","housing_slots":[],"created_at":"2026-01-25T12:16:18.611Z","updated_at":"2026-01-25T12:16:18.611Z"},{"id":35,"tile_id":846,"land_chunk_index":96,"name":"Village 846-96","housing_slots":[],"created_at":"2026-01-25T12:16:18.611Z","updated_at":"2026-01-25T12:16:18.611Z"},{"id":36,"tile_id":507,"land_chunk_index":76,"name":"Village 507-76","housing_slots":[],"created_at":"2026-01-25T12:16:18.611Z","updated_at":"2026-01-25T12:16:18.611Z"},{"id":37,"tile_id":1186,"land_chunk_index":87,"name":"Village 1186-87","housing_slots":[],"created_at":"2026-01-25T12:16:18.611Z","updated_at":"2026-01-25T12:16:18.611Z"},{"id":38,"tile_id":1139,"land_chunk_index":64,"name":"Village 1139-64","housing_slots":[],"created_at":"2026-01-25T12:16:18.611Z","updated_at":"2026-01-25T12:16:18.611Z"},{"id":39,"tile_id":76,"land_chunk_index":88,"name":"Village 76-88","housing_slots":[],"created_at":"2026-01-25T12:16:18.611Z","updated_at":"2026-01-25T12:16:18.611Z"},{"id":40,"tile_id":710,"land_chunk_index":17,"name":"Village 710-17","housing_slots":[],"created_at":"2026-01-25T12:16:18.611Z","updated_at":"2026-01-25T12:16:18.611Z"},{"id":41,"tile_id":75,"land_chunk_index":40,"name":"Village 75-40","housing_slots":[],"created_at":"2026-01-25T12:16:18.611Z","updated_at":"2026-01-25T12:16:18.611Z"},{"id":42,"tile_id":345,"land_chunk_index":19,"name":"Village 345-19","housing_slots":[],"created_at":"2026-01-25T12:16:18.611Z","updated_at":"2026-01-25T12:16:18.611Z"},{"id":43,"tile_id":876,"land_chunk_index":46,"name":"Village 876-46","housing_slots":[],"created_at":"2026-01-25T12:16:18.611Z","updated_at":"2026-01-25T12:16:18.611Z"},{"id":44,"tile_id":833,"land_chunk_index":77,"name":"Village 833-77","housing_slots":[],"created_at":"2026-01-25T12:16:18.611Z","updated_at":"2026-01-25T12:16:18.611Z"},{"id":45,"tile_id":1336,"land_chunk_index":98,"name":"Village 1336-98","housing_slots":[],"created_at":"2026-01-25T12:16:18.611Z","updated_at":"2026-01-25T12:16:18.611Z"},{"id":46,"tile_id":837,"land_chunk_index":29,"name":"Village 837-29","housing_slots":[],"created_at":"2026-01-25T12:16:18.611Z","updated_at":"2026-01-25T12:16:18.611Z"},{"id":47,"tile_id":346,"land_chunk_index":43,"name":"Village 346-43","housing_slots":[],"created_at":"2026-01-25T12:16:18.611Z","updated_at":"2026-01-25T12:16:18.611Z"},{"id":48,"tile_id":515,"land_chunk_index":55,"name":"Village 515-55","housing_slots":[],"created_at":"2026-01-25T12:16:18.611Z","updated_at":"2026-01-25T12:16:18.611Z"},{"id":49,"tile_id":899,"land_chunk_index":28,"name":"Village 899-28","housing_slots":[],"created_at":"2026-01-25T12:16:18.611Z","updated_at":"2026-01-25T12:16:18.611Z"},{"id":50,"tile_id":1353,"land_chunk_index":35,"name":"Village 1353-35","housing_slots":[],"created_at":"2026-01-25T12:16:18.611Z","updated_at":"2026-01-25T12:16:18.611Z"},{"id":51,"tile_id":1148,"land_chunk_index":26,"name":"Village 1148-26","housing_slots":[],"created_at":"2026-01-25T12:16:18.611Z","updated_at":"2026-01-25T12:16:18.611Z"},{"id":52,"tile_id":32,"land_chunk_index":3,"name":"Village 32-3","housing_slots":[],"created_at":"2026-01-25T12:16:18.611Z","updated_at":"2026-01-25T12:16:18.611Z"},{"id":53,"tile_id":557,"land_chunk_index":88,"name":"Village 557-88","housing_slots":[],"created_at":"2026-01-25T12:16:18.611Z","updated_at":"2026-01-25T12:16:18.611Z"},{"id":54,"tile_id":1363,"land_chunk_index":98,"name":"Village 1363-98","housing_slots":[],"created_at":"2026-01-25T12:16:18.611Z","updated_at":"2026-01-25T12:16:18.611Z"}]}
